{"windows":[{"fields":[{"data":"altitude_ft","x":0,"y":0,"size":2,"dec":0,"font":0,"prefix":"","suffix":" ft"},{"data":"vario_mps","x":0,"y":14,"size":1,"dec":2,"font":0,"prefix":"Climb ","suffix":" m/s"},{"data":"battery_pct","x":85,"y":55,"size":1,"dec":0,"font":0,"prefix":"Bat ","suffix":"%"},{"data":"wifi_status","x":0,"y":48,"size":1,"dec":0,"font":0,"prefix":"","suffix":""},{"data":"pitch_deg","x":0,"y":29,"size":1,"dec":0,"font":0,"prefix":"Pitch  ","suffix":""},{"data":"avg_speed_mph","x":0,"y":21,"size":1,"dec":0,"font":0,"prefix":"Avg speed ","suffix":""}]},{"fields":[{"data":"lat","x":0,"y":0,"size":1,"dec":6,"font":0,"prefix":"Lat ","suffix":""},{"data":"lng","x":0,"y":9,"size":1,"dec":6,"font":0,"prefix":"Lng ","suffix":""},{"data":"gps_speed_mph","x":0,"y":18,"size":1,"dec":1,"font":0,"prefix":"Spd ","suffix":" mph"},{"data":"sat_seen","x":103,"y":57,"size":1,"dec":0,"font":1,"prefix":"","suffix":""},{"data":"avg_speed_mph","x":0,"y":26,"size":1,"dec":0,"font":0,"prefix":"Avg speed ","suffix":" mph"},{"data":"flight_time","x":0,"y":34,"size":1,"dec":0,"font":0,"prefix":"Time: ","suffix":""},{"data":"battery_pct","x":0,"y":47,"size":1,"dec":0,"font":0,"prefix":"Battery %","suffix":""},{"data":"sat_used","x":66,"y":57,"size":1,"dec":0,"font":1,"prefix":"Sat  ","suffix":"/"}]},{"fields":[{"data":"temp_f","x":0,"y":0,"size":1,"dec":1,"font":0,"prefix":"T ","suffix":"F"},{"data":"humidity_pct","x":0,"y":9,"size":1,"dec":0,"font":0,"prefix":"H ","suffix":"%"},{"data":"battery_v","x":0,"y":19,"size":1,"dec":2,"font":0,"prefix":"Bat ","suffix":"V"},{"data":"date","x":0,"y":40,"size":1,"dec":0,"font":0,"prefix":"","suffix":""},{"data":"time","x":0,"y":52,"size":1,"dec":0,"font":0,"prefix":"","suffix":" UTC"},{"data":"flight_time","x":0,"y":28,"size":1,"dec":0,"font":0,"prefix":"Flight: ","suffix":""}]},{"fields":[{"data":"raw_altitude_ft","x":0,"y":0,"size":1,"dec":0,"font":0,"prefix":"r Alt: ","suffix":""},{"data":"altitude_ft","x":12,"y":8,"size":1,"dec":0,"font":0,"prefix":"Alt: ","suffix":""},{"data":"temp_f","x":75,"y":16,"size":1,"dec":0,"font":0,"prefix":"T: ","suffix":""},{"data":"humidity_pct","x":75,"y":25,"size":1,"dec":0,"font":0,"prefix":"H: ","suffix":""},{"data":"pitch_deg","x":0,"y":18,"size":1,"dec":0,"font":0,"prefix":"Pitch: ","suffix":""},{"data":"gps_speed_mph","x":0,"y":29,"size":1,"dec":0,"font":0,"prefix":"Speed: ","suffix":""},{"data":"avg_speed_mph","x":0,"y":37,"size":1,"dec":0,"font":0,"prefix":"Avg speed: ","suffix":""},{"data":"flight_time","x":0,"y":50,"size":1,"dec":0,"font":0,"prefix":"Flight: ","suffix":""}]}]}